README.md
setup.py
sep_service_caller/__init__.py
sep_service_caller/main.py
sep_service_caller/settings.py
sep_service_caller/utils.py
sep_service_caller.egg-info/PKG-INFO
sep_service_caller.egg-info/SOURCES.txt
sep_service_caller.egg-info/dependency_links.txt
sep_service_caller.egg-info/entry_points.txt
sep_service_caller.egg-info/requires.txt
sep_service_caller.egg-info/top_level.txt