Metadata-Version: 2.1
Name: sep-service-caller
Version: 0.1.0
Summary: Command line tool to call LCO source extraction service
Home-page: https://github.com/LCOGT/sep-service-caller
Author: Matt Daily
Author-email: mdaily@lco.global
License: UNKNOWN
Platform: UNKNOWN
